diskq/__init__.py
diskq/dqueue.py
diskq-1.0.0.dist-info/LICENSE
diskq-1.0.0.dist-info/METADATA
diskq-1.0.0.dist-info/WHEEL
diskq-1.0.0.dist-info/top_level.txt
diskq-1.0.0.dist-info/RECORD
