Metadata-Version: 2.1
Name: diskq
Version: 1.0.0
Summary: DiskQ is a Python package that provides persistent queues using disk storage
Home-page: https://github.com/Pactortester/diskq.git
Author: lijiawei
Author-email: jiawei.li2@qq.com
License: Apache License 2.0
Keywords: diskq,queue,persistentqueue,persist,disk,pqueue,diskqueue,tools
Platform: any
Classifier: Development Status :: 5 - Production/Stable
Classifier: Environment :: Console :: Curses
Classifier: Operating System :: MacOS
Classifier: Operating System :: POSIX
Classifier: Operating System :: Microsoft :: Windows
Classifier: Programming Language :: Python :: 3 :: Only
Classifier: Programming Language :: Python :: 3.6
Classifier: Programming Language :: Python :: 3.7
Classifier: Programming Language :: Python :: 3.8
Classifier: Programming Language :: Python :: 3.9
Classifier: Programming Language :: Python :: 3.10
Classifier: Programming Language :: Python :: 3.11
Classifier: Programming Language :: Python :: Implementation :: CPython
Requires-Dist: dill
